Workbook

Sheet output
A1: Normal | B1: Simple | C1: num_sentences_normal | D1: num_sentences_simple | E1: num_words_normal | F1: num_words_simple | G1: semantic_similarity | H1: coherence_normal | I1: coherence_simple | J1: information_preservation_score | K1: vocabulary_concreteness_measurement_normal | L1: vocabulary_concreteness_measurement_simple | M1: ambiguity_detection_normal | N1: ambiguity_detection_simple | O1: ai_explanation_completeness_present | P1: ai_explanation_completeness_count | Q1: ai_domain_terminology_present | R1: ai_domain_terminology_count | S1: ai_metaphor_appropriateness_present | T1: ai_metaphor_appropriateness_count | U1: ai_example_relevance_present | V1: ai_example_relevance_count | W1: ai_information_preservation_present | X1: ai_information_preservation_count
A2: Bei einer achtstündigen Razzia in einem Wohnhaus hoben Polizisten ein Lager von Neonazi-Artikeln aus. Dabei handelte es sich unter anderem um Schwibbögen, Räuchermännchen, Tassen, gravierte Gläser und Schieferplatten, Christbaumschmuck, Büsten, T-Shirts und Kalender. Zudem stellten sie neben den Handys und Tablets des Beschuldigten auch ein verbotenes Einhandmesser, einen Schlagring sowie eine Patrone sicher. Der 39-jährige Mieter der Wohnung muss sich nun wegen Verbreitung und Verwendung von Propagandamitteln verfassungswidriger Organisationen und Verstößen gegen das Waffengesetz verantworten. | B2: Dort hat die Polizei eine Razzia in der Wohnung von einem Mann gemacht. • Kissen, • Tassen, • Gläser • und Weihnachts-Schmuck. • Ein besonderes Messer, • einen Schlag-Ring • und eine Patrone für eine Schuss-Waffe . Der Mann hat sich nicht an das Waffen-Gesetz gehalten. | C2: 4 | D2: 7 | E2: 75 | F2: 38 | G2: 13.53 | H2: 0 | I2: 0 | J2: 0 | K2: 3 | L2: 1 | M2: 2 | N2: 0 | O2: 1 | P2: 1 | Q2: 1 | R2: 1 | S2: 0 | T2: 0 | U2: 0 | V2: 0 | W2: 1 | X2: 2
A3: Slackliner steigen Kulturhauptstadt Chemnitz mit Spanngurten aufs Dach. Am Donnerstag hat das 15. Slackfest auf dem Chemnitzer Theaterplatz begonnen. Auf dem Chemnitzer Theaterplatz sind Spanngurte zwischen den Kunstsammlungen, dem Opernhaus und dem Hotel "Chemnitzer Hof" gespannt. Seit 15 Jahren veranstaltet der Walden e.V. das Slackfest in Chemnitz, das damit das älteste seiner Art in Europa ist. Am Anfang sei es ein europäisches Festival gewesen und das solle es auch wieder werden, gerade im Hinblick auf die Kulturhauptstadt 2025. "Es geht darum, die Stadt sichtbarer zu machen", sagt Susan Endler von Team 2025 der Chemnitzer Wirtschafts- und Entwicklungsgesellschaft mbH (CWE), die das Projekt am Theaterplatz unterstützt hat. "Und die Stadt soll auch interessanter werden für europäische Sportler. | B3: Besondere Sport-Künstler steigen der Stadt Chemnitz aufs Dach. Am Donnerstag hat in Chemnitz ein besonderes Sportfest begonnen. Das Sportfest ist auf dem Theaterplatz. Sie laufen auf schmalen Gurten zwischen den Häusern hin und her. Seit 15 Jahren macht der Verein Walden das Slackfest in Chemnitz. Es ist das älteste Slackfest in Europa . Denn Chemnitz ist die Kultur-Hauptstadt vom Jahr 2025. Das soll bis zum Jahr 2025 so gemacht werden. Susan Endler arbeitet bei der Chemnitzer Wirtschafts- und Entwicklungs-Gesellschaft. Wir wollen die Stadt Chemnitz sichtbarer machen. Das bedeutet: Die Menschen sollen viele Orte von der Stadt sehen. | C3: 7 | D3: 12 | E3: 116 | F3: 96 | G3: 50.32 | H3: 0.29 | I3: 0.33 | J3: 0.5 | K3: 1 | L3: 1 | M3: 4 | N3: 5 | O3: 1 | P3: 1 | Q3: 1 | R3: 1 | S3: 1 | T3: 1 | U3: 0 | V3: 0 | W3: 1 | X3: 1
A4: Auch in diesem Jahr wird es im "Restaurant des Herzens" in Erfurt warmes Mittagessen zum Mitnehmen für Bedürftige geben. Hier können sich Bedürftige in der Weihnachts- und Winterzeit ein warmes Mittagessen abholen. Das "Restaurant des Herzens" wird aus Sach- und Geldspenden von Privatleuten, Unternehmen und Vereinen finanziert und geht in diesem Jahr in die 30. Saison. Bis zum 28. Januar werden zwischen 9.000 bis 11.000 Essen gekocht. | B4: Im Restaurant des Herzens in Erfurt können die Menschen warmes Essen bekommen. Dort gibt es ein Restaurant für Menschen: In diesem Jahr wird es schon zum 30. Mal gemacht. Hier können die Menschen wieder jeden Tag ein warmes Mittagessen bekommen. Von den Menschen aus Erfurt, • von Sport-Vereinen • und von Firmen. Das Restaurant soll bis zum Ende vom Monat Januar ge-öffnet sein. | C4: 4 | D4: 6 | E4: 67 | F4: 61 | G4: 45.91 | H4: 0.25 | I4: 0.33 | J4: 1 | K4: 0 | L4: 0 | M4: 1 | N4: 2 | O4: 0 | P4: 0 | Q4: 0 | R4: 0 | S4: 0 | T4: 0 | U4: 0 | V4: 0 | W4: 1 | X4: 2
A5: 141 Wolfswelpen in Sachsen geboren. Zwischen Mai 2020 und April 2021 sind in Sachsens Wäldern mindestens 87 Wolfswelpen geboren worden. Die Wölfe sind überwiegend in den bekannten Gebieten nachgewiesen worden. Es werde vermutet, dass es sich auch bei den Einzeltieren in den Territorien um Rudel handeln könnte, hieß es. Es konnte jedoch nicht abschließend geklärt werden, ob es sich dabei um eigenständige Vorkommen handelt oder ob diese Gebiete von benachbarten Rudeln mitgenutzt werden. | B5: Im Bundes-Land Sachsen sind 141 Wolf-Welpen geboren. Von Monat Mai im Jahr 2020 bis zum Monat April im Jahr 2021 sind in Sachen 87 Wolfs- Welpen geboren. Und vom Monat Mai im Jahr 2021 bis jetzt noch 54 Wolfs-Welpen dazu gekommen. Dass die Wölfe immer weniger Platz in den Wäldern haben. Denn es gibt bald zu viele Wolfs-Rudel in den Wäldern. Dann müssen sich die Wölfe um ihr Wolfs-Gebiet streiten. | C5: 5 | D5: 6 | E5: 73 | F5: 70 | G5: 28.33 | H5: 0.4 | I5: 0.33 | J5: 0.4 | K5: 0 | L5: 0 | M5: 5 | N5: 1 | O5: 0 | P5: 0 | Q5: 1 | R5: 1 | S5: 1 | T5: 1 | U5: 0 | V5: 0 | W5: 1 | X5: 1
A6: In der Lutherstadt Wittenberg muss die Wahl des neuen Oberbürgermeisters verschoben werden. Der ursprüngliche Termin Ende Februar wird wegen eines Formfehlers der Stadtverwaltung abgesagt, wie Bürgermeister und Wahlleiter Jochen Kirchner am Mittwoch bei einem Pressetermin bekanntgab. Demnach hat der Stadtrat lediglich den Termin beschlossen und nicht den Inhalt der Stellenbeschreibung. Die Kommunalaufsicht habe den Termin aufgrund dieses nicht mehr behebbaren Mangels verschoben. Neuer Wahltermin ist laut Kirchner der 24. April 2022. Dafür müssen nun bis zu 400 freiwillige Wahlhelferinnen und Wahlhelfer gefunden werden. | B6: In Wittenberg muss eine Wahl wann anders gemacht werden. In der Stadt Wittenberg muss eine Wahl zu einer anderen Zeit gemacht werden. Bei der Wahl ging es darum: Wer der neue Ober-Bürger-Meister von Wittenberg wird. Aber der Bürger-Meister Jochen Kirchner hat am Mittwoch gesagt: Die Stadt-Verwaltung hat bei der Wahl einen Fehler gemacht. Die Stadt-Verwaltung hat nicht auf-geschrieben: Die neue Wahl wird am 24. April 2022 gemacht. Dafür braucht die Stadt noch 400 Wahl-Helfer . | C6: 7 | D6: 8 | E6: 83 | F6: 74 | G6: 30.82 | H6: 0.29 | I6: 0.38 | J6: 0.83 | K6: 2 | L6: 2 | M6: 1 | N6: 1 | O6: 0 | P6: 0 | Q6: 1 | R6: 1 | S6: 0 | T6: 0 | U6: 0 | V6: 0 | W6: 1 | X6: 1
A7: An die Bewohnerinnen und Bewohner der Wohnanlage Othmarscher Kirchenweg 6 + 8 + 8a (…) Entfernung privater Spielplatzgeräte Diese erfüllen nicht die DIN EN 1176 und sind für den öffentlichen gebrauch nicht geeignet und müssen abgebaut werden. Der Eigentümer / Die Eigentümer des Spielgerätes / der Spielgeräte (Trampolin, Holzpferd, etc.) muss / müssen bitte die Spielgeräte innerhalb von 7 Tagen (…) abbauen. Für die Nachkontrolle (Prüfung) werden Gebühren in jedem Fall anfallen. | B7: Othmarscher Kirchenweg 6 + 8 + 8a Liebe Leute vom Othmarscher Kirchenweg 6 + 8 + 8a! Aber diese Spiel·Sachen sind nicht sicher. Andere Leute dürfen damit nicht schaukeln oder hüpfen. Das muss dann der Besitzer von den Spiel·Sachen zahlen. Die Kontrolle kostet auf jeden Fall Geld. | C7: 6 | D7: 5 | E7: 67 | F7: 47 | G7: 18.73 | H7: 0.17 | I7: 0.4 | J7: 0.17 | K7: 2 | L7: 0 | M7: 1 | N7: 0 | O7: 1 | P7: 1 | Q7: 1 | R7: 2 | S7: 0 | T7: 0 | U7: 0 | V7: 0 | W7: 1 | X7: 2
A8: Bei einer Struma handelt es sich um eine vergrößerte Schilddrüse . Das schmetterlingsförmige Organ befindet sich im vorderen Teil des Halses und liegt der Luftröhre auf. Die Schilddrüse bildet Hormone und beeinflusst darüber zahlreiche Stoffwechselvorgänge und Organe im Körper. Dafür benötigt die kleine Drüse das Spurenelement Jod. Bekommt die Schilddrüse zu wenig Jod, kann sie nicht mehr genügend Hormone bilden. Es entstehen Schilddrüsenknoten, Mediziner sprechen von einer Struma nodosa. In beiden Fällen wird die Vergrößerung des Organs ab einem gewissen Volumen von außen sichtbar. Steht die Diagnose Kropf fest, muss er in der Regel behandelt werden. die Einnahme von Medikamenten, eine Behandlung mit radioaktivem Jod (Radiojodtherapie) oder eine Operation an der Schilddrüse. Schwangere und Stillende, die einen erhöhten Bedarf haben, sollten mit Ihrem Arzt über eine eventuell notwendige Nahrungsergänzung sprechen. | B8: Bei einem Kropf ist die Schilddrüse vergrößert. Die Schilddrüse befindet sich unter dem Kehlkopf an der Luftröhre. Die Schilddrüse produziert wichtige Hormone. Diese Hormone beeinflussen wichtige Körperfunktionen Die Schilddrüse benötigt Jod zum Arbeiten. Die Schilddrüse bekommt nicht genug Jod? Dann kann die Schilddrüse nicht mehr genug Hormone produzieren. Deshalb wird die Schilddrüse größer. Aber die Schilddrüse arbeitet trotzdem normal? Die Schilddrüse ist vergrößert und die Schilddrüse produziert nicht mehr genug Hormone? Die Schilddrüse braucht Jod. Der Körper kann Jod nicht selbst herstellen. Deshalb nimmt eine Person vielleicht nicht genug Jod durch Lebensmittel auf. Die Schilddrüse bekommt nicht genug Jod? Dann kann die Schilddrüse nicht mehr genug Hormone produzieren. Deshalb wird die Schilddrüse größer. Manchmal wird die Schilddrüse insgesamt größer. Dann entstehen Knoten in der Schilddrüse. Ab einer bestimmten Größe kann man die vergrößerte Schilddrüse sogar von außen sehen. Dann muss der Kropf meist behandelt werden. Für die Behandlung gibt es verschiedene Möglichkeiten: Medikamente Behandlung mit radioaktivem Jod Operation Sprechen Sie mit Ihrem Arzt. | C8: 9 | D8: 22 | E8: 129 | F8: 163 | G8: 58.87 | H8: 0.11 | I8: 0.82 | J8: 0.4 | K8: 4 | L8: 3 | M8: 4 | N8: 2 | O8: 1 | P8: 1 | Q8: 1 | R8: 1 | S8: 0 | T8: 0 | U8: 0 | V8: 0 | W8: 1 | X8: 1
A9: Sie ziehen um nach Köln? Dann müssen Sie sich bei uns anmelden. Die Anmeldung können Sie innerhalb von 14 Tagen nach dem Einzug mit vorheriger Terminvereinbarung in einem Kundenzentrum Ihrer Wahl vornehmen. Bei einer Anmeldung im Familienverband benötigen wir die Ausweisdokumente aller zuziehenden Personen Anmeldeformular mit Unterschrift der oder des Meldepflichtigen Sie erhalten das Formular in den Kundenzentren oder unter Downloads und Infos zum Herunterladen. Wenn Sie persönlich vorsprechen und die Anmeldung nicht durch eine bevollmächtigte Person erfolgt, benötigen Sie kein Anmeldeformular. Wenn Sie aus dem Ausland zuziehen und verheiratet oder verpartnert sind, bringen Sie bitte Ihre Eheurkunde (Auszug aus dem Eheregister) oder Lebenspartnerschaftsurkunde mit. Bei ausländischen Urkunden wird zudem eine Übersetzung durch eine Dolmetscherin, einen Dolmetscher, eine Übersetzerin oder einen Übersetzer benötigt. Urkunden und Übersetzungen müssen im Original vorgelegt werden. Bei einer Abmeldung beziehungsweise einem Auszug ist dies nicht erforderlich. Bis wann und wo muss ich mich anmelden? Wenn Sie eine Wohnung beziehen, müssen Sie sich innerhalb von 14 Tagen nach dem Einzug anmelden. Wenn Sie aus dem Ausland zuziehen, kann an Ihrer Stelle keine bevollmächtigte Person vorsprechen. Leider dürfen Sie aus rechtlichen Gründen das Anmeldeformular nicht auf dem Postweg übersenden. Die Anmeldung ist gebührenfrei. | B9: Sie ziehen nach Köln um? Dann müssen Sie Ihre neue Adresse bei uns anmelden. Spätestens 2 Wochen nach dem Umzug zur neuen Adresse müssen Sie sich anmelden. Die Adressen von allen Kunden-Zentren in Köln finden Sie unter der Überschrift: Sie brauchen dazu: Ihren Personal-Ausweis oder Ihren Reise-Pass die Ausweise von allen Personen, die mit Ihnen umziehen das Anmelde-Formular Bestätigung vom Vermieter oder der Vermieterin. Dann müssen Sie die Bestätigung nicht abgeben. Wenn Sie eine Wohnung kaufen. Oder schreibt für Sie eine Urkunde. Wichtig: Sie müssen beide Formulare unterschreiben . Sie müssen beide Formulare und alle anderen Papiere mitbringen. Als verheirateter Mensch oder als Mensch, der in einer Lebens-Partnerschaft lebt, brauchen Sie dann zusätzlich: Ehe-Urkunde / Kopie aus dem Ehe-Register oder Lebens-Partnerschafts-Urkunde Geburts-Urkunden von Ihren Kindern , die mit Ihnen umziehen. Wichtig: Wenn Sie Urkunden aus dem Ausland vorzeigen müssen, beachten Sie bitte: Das muss eine Übersetzerin oder ein Übersetzer machen. Oder eine Dolmetscherin oder ein Dolmetscher. Er prüft die Übersetzer und Dolmetscher. Sie dürfen als Übersetzer oder Dolmetscher arbeiten. Wichtig: Urkunden und Übersetzungen müssen im Original vorgelegt werden. Wichtig ist auch: Was ist, wenn ich zum Anmelden nicht selber kommen kann? Wenn Sie innerhalb von Deutschland umziehen, dann kann jemand anderes für Sie zu uns kommen. Diesem Menschen müssen Sie vertrauen. Auf dem Papier erlauben Sie einem Menschen, etwas für Sie zu tun. Den Namen von diesem Menschen schreiben Sie auf das Papier. Sie müssen das Papier unterschreiben. Sie können das nämlich nicht selber tun, weil Sie zum Beispiel krank im Bett liegen. Es passiert nichts damit, was Sie nicht wollen. Widersprechen können Sie beim Anmelden von Ihrem Wohnsitz. Sie können aber auch später noch dem Weitergeben von Ihren Daten widersprechen. An bestimmte Stellen dürfen wir Ihre Daten nur dann weitergeben, wenn Sie der Weitergabe zugestimmt haben. Zum Beispiel: Sie kommen nur dann ins Telefon-Buch, wenn Sie dem zugestimmt haben. Wenn nicht, darf man Sie nicht ins Telefon-Buch schreiben. Das Anmelden von Ihrem Wohnsitz ist kostenlos. | C9: 16 | D9: 33 | E9: 196 | F9: 323 | G9: 24.22 | H9: 0.12 | I9: 0.33 | J9: 0.43 | K9: 8 | L9: 4 | M9: 16 | N9: 40 | O9: 0 | P9: 0 | Q9: 1 | R9: 1 | S9: 0 | T9: 0 | U9: 0 | V9: 0 | W9: 1 | X9: 1
A10: Die Ausstellung zum tschechisch-deutschen Märchenfilm "Drei Haselnüsse für Aschenbrödel", der auch auf Schloss Moritzburg gedreht wurde, ist längst ein Klassiker und Publikumsrenner um Weihnachten. Viele Fans würden wohl auch kommen, um in den barocken Schlossräumen ein bisschen Prinz oder Prinzessin zu spielen, zu lustwandeln und sich an Aschenbrödels Welt zu erfreuen. 20 Originalkostüme aus dem Aschenbrödel-Film und weitere 16 originale und wirklich wunderschöne Kleider werden ausgestellt, die Schauspielerin Libuše Šafránková in sehr unterschiedlichen Rollen getragen hat. In über 60 Filmen und Serien hat die im Juni 2021 verstorbene Šafránková mitgespielt. Sie hat wirklich in allen Genres gespielt und wir haben aus jedem Beispiele dabei, beschreibt Fliegler ihre Vielfalt: | B10: Auf Schloss Moritzburg gibt es eine Ausstellung über Aschenbrödel. Das war der Märchen-Film: 3 Haselnüsse für Aschenbrödel. Deshalb gibt es in jedem Jahr auf Schloss Moritzburg eine Ausstellung zu dem Märchen-Film. Und sie können sich selbst ein Bisschen so fühlen wie ein Prinz oder eine Prinzessin . In dem Märchen-Film hat die Schauspielerin : Libuše Šafránková mit-gespielt. Aber im Jahr 2021 ist die Schauspielerin gestorben. Sie hat gesagt: | C10: 5 | D10: 7 | E10: 108 | F10: 66 | G10: 35.36 | H10: 0.4 | I10: 0.43 | J10: 0.5 | K10: 1 | L10: 2 | M10: 2 | N10: 5 | O10: 0 | P10: 0 | Q10: 1 | R10: 1 | S10: 1 | T10: 1 | U10: 0 | V10: 0 | W10: 1 | X10: 2
A11: Mann stirbt nach Böller-Explosion im Saale-Holzland-Kreis. Der Mann sei in der Nähe des Böllers gewesen, als dieser explodierte, teilte die Polizei am Sonntag auf Anfrage mit. Ob er den Feuerwerkskörper selbst gezündet habe und ob es sich um einen Eigenbau oder Import handelte, werde derzeit noch ermittelt, sagte ein Sprecher . | B11: Ein Mann im Saale-Holzland-Kreis ist bei einer Explosion gestorben. Aber die Polizei hat am Sonntag gesagt: • Ob er den Böller selber gebaut hat. • Oder ob er den Böller aus einem anderen Land gekauft hat. | C11: 3 | D11: 4 | E11: 50 | F11: 34 | G11: 49.54 | H11: 0.33 | I11: 0.25 | J11: 0.33 | K11: 0 | L11: 0 | M11: 3 | N11: 2 | O11: 0 | P11: 0 | Q11: 0 | R11: 0 | S11: 0 | T11: 0 | U11: 0 | V11: 0 | W11: 1 | X11: 1
A12: Besenreiser sind erweiterte, winzige Venen, die in der Haut verlaufen und von außen sichtbar sind. Sie sind eine Form von Krampfadern . Deshalb sollten Sie vorsichtshalber einen Arzt aufsuchen auch, wenn Sie unsicher sind, ob es sich um Besenreiser handelt. Frauen sind häufiger betroffen als Männer. Auslöser ist eine Bindegewebsschwäche. Betrifft der dadurch entstehende Rückstau die kleinsten Hautvenen, werden sie als Besenreiser unter der Haut sichtbar. Versackt das Blut in diesen winzigen Gefäßen, beeinträchtigt dies im Normalfall nicht die Durchblutung in den Beinen. Besenreiser treten vor allem an den Beinen auf, manchmal aber auch im Gesicht, auf der Nase oder an der Brust. Bevor dies geschieht, untersucht er die Venen mit einem speziellen Ultraschallgerät. Es gibt verschiedene Methoden, mit denen Ärzte und Ärztinnen die Besenreiser beseitigen: Sie können in die winzigen Venen ein Mittel geben, durch welches diese veröden. Das Medikament bewirkt, dass die Venenwände der Besenreiser verkleben und nicht mehr durchblutet werden. Manchmal kann sich die Haut an der betreffenden Stelle bräunlich verfärben. Hierbei werden die Besenreiser durch die Energie des Lasers verödet. Narben hinterlässt das Lasern nicht, zu Pigmentveränderungen der Haut kann es jedoch auch kommen. Der Patient oder die Patientin muss im Anschluss ebenfalls für eine gewisse Zeit einen Kompressionsstrumpf anziehen und mehrere Behandlungstermine einplanen. | B12: Besenreiser sind sehr kleine Blutgefäße. Besenreiser sind eine Form von Krampfadern . Dann können auch Sie eher Besenreiser oder Krampfadern bekommen. Frauen bekommen häufiger Besenreiser oder Krampfadern als Männer. Bindegewebsschwäche . Der Stau macht die kleinen Blutgefäße unter der Haut sichtbar. Besonders betroffen sind oft die Venen in den Beinen. Besenreiser an den Beinen sind besonders häufig. Sie kommen manchmal auch im Gesicht oder im Bereich der Brust vor. Der Venen-Spezialist untersucht Sie mit einem Ultraschallgerät. Dann kann der Venen-Spezialist die Besenreiser mit verschiedenen Methoden entfernen wie zum Beispiel: Sklerosierung Laser-Therapie Bei einer Sklerosierung gibt der Venen-Spezialist ein Mittel in die Venen der Besenreiser. Dieses Mittel verklebt die Wände der Venen. Die Venen werden dann nicht mehr durchblutet. Nach wenigen Wochen kann man die Venen dann nicht mehr sehen. Aber die Haut kann sich an den betroffenen Stellen manchmal bräunlich färben. Bei der Laser-Therapie entfernt die Energie von Laserstrahlen die Besenreiser. Der Laser hinterlässt keine Narben. Aber manchmal verändert der Laser die Farbe der Haut. Der Arzt kann die Sklerosierung und die Laser-Therapie auch kombinieren. | C12: 16 | D12: 21 | E12: 207 | F12: 173 | G12: 67.11 | H12: 0.06 | I12: 0.43 | J12: 0.29 | K12: 1 | L12: 3 | M12: 12 | N12: 3 | O12: 1 | P12: 1 | Q12: 1 | R12: 1 | S12: 0 | T12: 0 | U12: 0 | V12: 0 | W12: 1 | X12: 1
A13: Die klassischen Symptome der Krätze stellen sich beim ersten Mal üblicherweise erst zwei bis fünf Wochen nach der Übertragung der Parasiten ein. Krätzmilben bevorzugen warme Hautregionen, an denen die oberste Hautschicht besonders dünn ist. Die entzündlichen Veränderungen der Haut treten daher bevorzugt zwischen den Fingern und Zehen, in der Achselgegend, im Bereich des Nabels oder des Brustwarzenhofes, an Knöcheln und inneren Fußrändern sowie der Genitalregion auf. Bei Säuglingen und Kleinkindern kommt Krätze aber auch auf der behaarten Kopfhaut und den Hand- und Fußflächen vor. An den betroffenen Hautstellen ist die Haut gerötet, sie kann leicht brennen. Es bilden sich stecknadelgroße Knötchen, bei kleinen Kindern gelegentlich auch Bläschen. Das Ziel ist, alle vorhandenen Krätzmilben in und auf der Haut abzutöten. Wäscht man sie bei 60 °C, werden normalerweise alle noch vorhandenen Skabiesmilben abgetötet. Textilien, die nicht gewaschen werden dürfen, am besten über vier Tage bei Raumtemperatur in einem luftdicht verschlossenen Plastiksack verstauen, bis die Milben abgestorben sind. Von Polstermöbeln geht üblicherweise keine Gefahr mehr aus, wenn sie gründlich abgesaugt und etwa drei bis vier Tage lang nicht benutzt werden. Normalerweise muss und kann man einer Krätze nicht vorbeugen. | B13: Parasiten verursachen die ansteckende Erkrankung. Deshalb erkennt man Krätze oft erst nach zwei bis sechs Wochen. Krätzmilben mögen warme Hautregionen mit einer dünnen obersten Hautschicht. Deshalb graben Krätzmilbenihre Gänge oft an diesen Stellen: zwischen den Fingern oder Zehen im Achselbereich am Bauchnabel am Brustwarzenhof an den Knöcheln im Genitalbereich Bei Babys und Kleinkindern kann Krätze auch an anderen Stellen vorkommen. Kopfhaut Handflächen Es gibt aber auch Tabletten zum Einnehmen. Die Medikamente töten die Krätzmilben in und auf der Haut ab. Auf diese Dinge ist außerdem zu achten: Wäsche waschen bei 60 Grad: Waschen Sie Bettwäsche, Handtücher und Unterwäsche bei 60 Grad. Einige Sachen dürfen nicht gewaschen werden. Verschließen Sie Sachen aus Wolle deshalb in einem Plastiksack. Nach etwa vier Tagen können Sie die Sachen aus dem Plastiksack herausnehmen. Außerdem sollten Sie die Polstermöbel vier Tage nicht benutzen. Aus diesem Grund kann man sich zum Beispiel auch auf einer Reise mit Krätze anstecken. | C13: 11 | D13: 17 | E13: 188 | F13: 152 | G13: 37.64 | H13: 0.09 | I13: 0.24 | J13: 0.33 | K13: 1 | L13: 1 | M13: 4 | N13: 5 | O13: 1 | P13: 1 | Q13: 1 | R13: 1 | S13: 0 | T13: 0 | U13: 0 | V13: 0 | W13: 1 | X13: 1
... A500: Wir fördern im sozialen Bereich die Arbeit von Selbsthilfegruppen. Im sozialen Bereich beschäftigen sich Selbsthilfegruppen mit sozialen und psychosozialen Themenkreisen wie zum Beispiel: Familie und Partnerschaft Frauenselbsthilfe Alter und/oder Behinderung Lebensführung Essstörungen Misshandlung Flucht und Asyl Das Gesundheitsamt fördert finanziell Gruppen im Gesundheitsbereich. Beratung durch die Selbsthilfe-Kontaktstelle Köln (ehemals KISS) Die Kontakt- und Informationsstelle für Selbsthilfegruppen in Köln berät: Betroffene und Angehörige Selbsthilfegruppen Sie vermittelt in Selbsthilfegruppen, unterstützt bei Gruppengründungen und leistet Öffentlichkeitsarbeit. Sie Sie Sie Sie | B500: Wir unterstützen Selbsthilfe-Gruppen im sozialen Bereich. Selbsthilfe heißt: Menschen versuchen sich selbst und anderen zu helfen. Zum Beispiel: Familie Trennung Flucht Ess-Störungen Misshandlung Es gibt auch Selbsthilfe-Gruppen im Bereich Gesundheit. Selbsthilfe-Kontaktstelle Köln (ehemals KISS) Es gibt eine Kontakt-Stelle für Selbsthilfe in Köln: Die Adresse der Kontakt-Stelle ist: Selbsthilfe-Kontaktstelle Köln Marsilstein 4-6 50676 Köln Die Kontakt-Stelle berät: Betroffene Angehörige Selbsthilfe-Gruppen Vertreter und Vertreterinnen von den Medien Sie vermittelt Menschen in Selbsthilfe-Gruppen. Sie unterstützt bei der Gründung von Selbsthilfe-Gruppen. Das heißt: Wenn Sie eine neue Gruppe machen wollen. Dann bekommen Sie Hilfe und Beratung. Das heißt: Sie schreibt Presse-Mitteilungen. Hier finden Sie den Link zu der Selbsthilfe-Kontaktstelle Köln: Selbsthilfe im Internet Hier finden Sie Links zum Thema Selbsthilfe. Infos zur Förderung bekommen Sie im Amt für Soziales und Senioren. Sie können uns auch anrufen. Sie müssen nichts bezahlen. | C500: 12 | D500: 20 | E500: 78 | F500: 137 | G500: 29.48 | H500: 0.25 | I500: 0.2 | J500: 0.62 | K500: 5 | L500: 6 | M500: 6 | N500: 16 | O500: 0 | P500: 0 | Q500: 0 | R500: 0 | S500: 0 | T500: 0 | U500: 0 | V500: 0 | W500: 0 | X500: 0
A501: Hilfe für Opfer - Recht auf Soziale Entschädigung Passiert doch etwas, hilft das Recht auf Soziale Entschädigung.“ | B501: Recht auf Soziale Entschädigung Was ist das Recht auf Soziale Entschädigung? Dann haben sie das Recht auf Soziale Entschädigung. Aber nicht jeder Mensch, der etwas Schlimmes erlebt hat, hat dieses Recht. Wer hat das Recht auf Soziale Entschädigung? Was ändert sich an dem Recht auf Soziale Entschädigung? | C501: 1 | D501: 6 | E501: 16 | F501: 47 | G501: 83.86 | H501: 0 | I501: 0.83 | J501: 0 | K501: 2 | L501: 5 | M501: 0 | N501: 1
A502: Sie kommen dahin zurück, wo Sie Ihr Auto abgestellt haben und das Auto ist weg. Es wurde vermutlich entweder abgeschleppt oder gestohlen. An wen können Sie sich wenden? Ob und wohin das Fahrzeug abgeschleppt worden ist, erfahren Sie von der Verkehrsüberwachungskraft, sofern diese noch vor Ort ist, ansonsten beim Verkehrsdienst der Stadt Köln Servicetelefon Willy-Brandt-Platz 3 50679 Köln 32000 Erreichbarkeit des Servicetelefons: Montag bis Donnerstag, 7 bis 1 Uhr Freitag, 7 bis 2 Uhr Samstag, 9 bis 2 Uhr Sonntag, 9:30 bis 1 Uhr Feiertag, 10 bis 24 Uhr Außerhalb dieser Zeiten wenden Sie sich bitte an die Polizei Köln unter der Rufnummer 0221 / 229- 0. Wenn feststehen sollte, dass weder der Ordnungs- und Verkehrsdienst noch die Polizei ein Abschleppen Ihres Fahrzeugs veranlasst haben, dann könnte es gestohlen worden sein. Wo können Sie Ihr Fahrzeug abholen? Bitte erfragen Sie zunächst in jedem Fall bei der Funkzentrale des Ordnungs- und Verkehrsdienstes (Rufnummer siehe oben), welche der hier folgenden Abschleppfirmen Ihr Fahrzeug abgeschleppt hat und wo es bis zur Abholung steht. Firma Colonia Mathias-Brüggen-Straße 68 50827 Köln-Ossendorf Telefon: 0221 / 956860 Firma Schlimbach Bergisch Gladbacher Straße 240 51063 Köln-Buchheim Telefon: Telefax: 0221 / 800180-10 Firma Pahlke Möhlstraße 28 51069 Köln-Dellbrück Wenn Sie das Auto bei der Abschleppfirma abholen wollen, müssen Sie folgendes bereithalten: Rechtliche Voraussetzungen 77 Verwaltungsvollstreckungsgesetz Nordrhein-Westfalen (NW) in Verbindung mit 7a und 11 der Kostenordnung Nordrhein-Westfalen (NW) | B502: Ihr Auto ist weg? Es steht nicht mehr da, wo Sie es abgestellt haben? Dann wurde Ihr Auto vielleicht abgeschleppt. Oder Ihr Auto wurde gestohlen . Auf dieser Seite erklären wir, was Sie tun können. Manchmal ist der Ordnungs- und Verkehrs-Dienst noch vor Ort. Ob und wohin Ihr Fahrzeug abgeschleppt wird. Service-Telefon: 02 21 / 22 13 20 00 Ordnungs- und Verkehrs-Dienst der Stadt Köln Willy-Brandt-Platz 3 50679 Köln Sie können zu diesen Zeiten beim Service-Telefon anrufen: Montag bis Donnerstag 7 bis 0 Uhr Freitag 7 bis 1 Uhr Samstag 9 bis 1 Uhr Sonntage und Feiertage 9 bis 0 Uhr Außerhalb dieser Zeiten rufen Sie bitte die Polizei Köln . Wichtig: Wenn die Polizei und der Ordnungs- und Verkehrs-Dienst keine Infos zu Ihrem Fahrzeug haben, dann wurde es vielleicht gestohlen . Und Sie müssen den Diebstahl anzeigen . Wo kann ich mein Fahrzeug abholen? Bitte fragen Sie nach: Welche Firma hat mein Fahrzeug abgeschleppt? Firma Colonia Mathias-Brüggen-Straße 68 50827 Köln-Ossendorf Telefon: 02 21 / 95 68 60 Firma Schlimbach Bergisch Gladbacher Straße 240 51063 Köln-Buchheim Telefon: 02 21 / 96 44 490 Firma Christophorus Höninger Weg 4 bis 10 50969 Köln-Zollstock Telefon: 02 21 / 80 01 800 Telefax: 02 21 / 80 01 80 10 Firma Pahlke Möhlstraße 28 51069 Köln-Dellbrück Telefon: 02 21 / 96 84 740 F irma Pahlke Hansestraße 9 51149 Köln-Gremberghoven Telefon: 0 22 03 / 18 69 30 6 Wenn Sie das Auto bei der Abschlepp-Firma abholen wollen, müssen Sie diese Papiere mitbringen: Ihren Personal-Ausweis den Fahrzeug-Schein vom abgeschleppten Fahrzeug. Damit können Sie der Abschlepp-Firma zeigen: Wichtig: Sie können die Abschlepp-Kosten sofort bezahlen . Das heißt: Sie zahlen sofort bei der Abschlepp-Firma. Wenn Sie nicht sofort bezahlen , bekommen Sie Ihr Fahrzeug nicht sofort zurück . Oder ob Ihr Fahrzeug bei der Abschlepp-Firma bleibt. Das ist das Geld für die Abschlepp-Firma. Wie viel Sie bezahlen müssen, hängt von vielen Fragen ab: Was für ein Fahrzeug haben Sie? Wie lange steht Ihr Fahrzeug bei der Abschlepp-Firma? Sie können bei der Abschlepp-Firma anrufen . Wenn die Abschlepp-Firma beauftragt worden ist, müssen Sie immer Geld bezahlen. Auch wenn Sie Ihr Fahrzeug umparken, bevor der Abschlepp-Wagen kommt. Aber Sie müssen die Fahrt vom Abschlepp-Wagen bezahlen. Oder Sie bekommen eine Anzeige . Dann müssen Sie eine Geld-Buße zahlen. Allgemein gilt: Sie müssen weniger Verwaltungs-Gebühren zahlen, wenn Sie direkt bei der Abschlepp-Firma bezahlen . Sie müssen nicht ins Amt kommen. Dann müssen Sie uns das Geld überweisen . Verwaltungs-Vollstreckungs-Gesetz Nord-Rhein-Westfalen Paragraf 77 Kosten-Ordnung Nord-Rhein-Westfalen Paragraf 7a und 11 | C502: 15 | D502: 44 | E502: 226 | F502: 401 | G502: 54.75 | H502: 0.27 | I502: 0.32 | J502: 0.8 | K502: 4 | L502: 1 | M502: 13 | N502: 33 | O502: 1 | P502: 1 | Q502: 1 | R502: 1 | S502: 0 | T502: 0 | U502: 0 | V502: 0 | W502: 1 | X502: 1
A503: Dies gilt nicht, wenn Sie bereits einen Reisepass besitzen. Sie können Ihren Personalausweis oder Reisepass in jedem Kundenzentrum in Köln beantragen, unabhängig von Ihrem Wohnort. Ihr Reisepass Der Reisepass wird benötigt, wenn Ihr bisheriger Ausweis verloren ging oder für den Fall, dass Sie bislang keinen Personalausweis besessen haben. Geburts-, Ehe- oder Lebenspartnerschaftsurkunde Bitte bringen Sie vorsorglich eine Urkunde beziehungsweise das Familienstammbuch mit. Wenn Sie verheiratet, verpartnert, geschieden oder verwitwet sind, wird anstelle der Geburtsurkunde (Auszug aus dem Geburtsregister) die Eheurkunde (Auszug aus dem Eheregister) beziehungsweise Lebenspartnerschaftsurkunde benötigt. Bei ausländischen Urkunden wird zudem eine Übersetzung durch eine*n Dolmetscher*in oder eine*n Übersetzer*in benötigt. Urkunden und Übersetzungen müssen im Original vorgelegt werden. Ein aktuelles biometrietaugliches Passfoto Einen vorläufigen maschinenlesbaren Personalausweis bekommen Sie sofort ausgehändigt, wenn Sie alle erforderlichen Unterlagen vorlegen können. Personalausweis fertig? Da Sie den PIN-Brief bei der Abholung nicht benötigen, bringen Sie ihn bitte nicht mit, sondern verwahren ihn sicher zu Hause. Die elektronische Abfrage, ob der Personalausweis fertig ist, ist jedoch möglich. Bitte denken Sie daran, dass bei der Abholung der bisherige Personalausweis oder vorläufige Personalausweis des Kindes vorgelegt werden muss. Jugendliche, die während der Gültigkeitsdauer ihres Ausweises 16 Jahre alt werden, können ab diesem Zeitpunkt die Online-Ausweisfunktionen und die persönliche PIN einschalten lassen. Informationen finden Sie vorab auch schon hier: Sie können auch online Ihren Online -Ausweis aktivieren. Ein Formular zur Beantragung der Befreiung können Sie im Downloadservice herunterladen. Bitte denken Sie daran, der bevollmächtigten Person auch Ihren bisherigen Personalausweis mitzugeben. Minderjährige unter 16 Jahren können einen Personalausweis weder eigenständig beantragen noch abholen. Gebühren 22,80 Euro für Personen unter 24 Jahren 37 Euro für Personen ab 24 Jahren 10 Euro für einen vorläufigen Personalausweis Ändern der Anschrift bei Umzug Die Gebühren können Sie bar oder mit der Girocard ( EC -Karte) und PIN-Nummer bezahlen. | B503: Dann müssen Sie einen Personal-Ausweis haben. Also einen Personal-Ausweis oder einen Reise-Pass. Oder zu einem anderen Kunden-Zentrum in Köln. Dann brauchen wir Ihren Reise-Pass . Oder Ihren Kinder-Reise-Pass , wenn Sie einen haben. Eine Urkunde oder das Familien-Stammbuch Bitte bringen Sie immer Ihr Familien-Stammbuch mit. Wenn Sie verheiratet oder geschieden sind: Dann brauchen wir Ihre Ehe-Urkunde. Wenn Sie in einer Lebens-Partnerschaft leben: Dann brauchen wir Ihre Lebens-Partnerschafts-Urkunde . Dann brauchen Sie eine Übersetzung von einem staatlich anerkannten Übersetzer. Wichtig: Sie müssen uns das Original von der Urkunde und das Original von der Übersetzung zeigen. Ein biometrisches Pass-Foto. Wenn Sie nicht so lange warten können, dann können wir Ihnen für die Zeit dazwischen einen vorläufigen Personal-Ausweis geben. Den vorläufigen Ausweis bekommen Sie sofort . Wenn Sie Ihren neuen Personal-Ausweis abholen, müssen Sie den vorläufigen Ausweis wieder abgeben. Der neue Personal-Ausweis ist nach 3 bis 4 Wochen fertig. Den Brief müssen Sie zu Hause gut aufheben. Die PIN -Nummer ist eine geheime Nummer, die nur Sie kennen. Ausweisen bedeutet, dass Sie sagen: Sie müssen mindestens 15 Jahre und 9 Monate alt sein: Sie bekommen auch ein geheimes Kenn-Wort . Dort erfahren Sie auch, wann genau Sie Ihren Personal-Ausweis abholen können. Dazu müssen Sie eine Nummer eingeben. Wenn Sie den Personal-Ausweis nicht selbst abholen können: Sie können die Vollmacht direkt im Internet ausfüllen. In dieser Vollmacht müssen Sie auch sagen: Ich habe den Brief von der Bundes-Druckerei erhalten. Dann fragen Sie bitte Jemanden. Ausnahme: Wenn Sie noch nicht 24 Jahre alt sind: 37 Euro: wenn Sie über 24 Jahre alt sind. 10 Euro : für einen vorläufigen Personal-Ausweis. 6 Euro: für das Freischalten im Internet, wenn Sie 16 Jahre alt werden. Wenn Sie Ihre Daten bei einem Umzug ändern müssen. Das heißt: Sie können mit Geld-Scheinen und Münzen bezahlen. Sie können auch mit Ihrer EC -Karte bezahlen. Sie können damit ohne Bar-Geld bezahlen. | C503: 24 | D503: 35 | E503: 294 | F503: 304 | G503: 25.72 | H503: 0.33 | I503: 0.2 | J503: 0.39 | K503: 5 | L503: 3 | M503: 19 | N503: 38 | O503: 1 | P503: 1 | Q503: 1 | R503: 1 | S503: 0 | T503: 0 | U503: 0 | V503: 0 | W503: 1 | X503: 1
A504: Als alleinerziehender Elternteil können Sie Leistungen nach dem Unterhaltsvorschussgesetz für Ihr Kind beantragen. Voraussetzung hierfür ist, dass der andere Elternteil, bei dem das Kind nicht lebt, keinen oder einen zu geringen Unterhalt zahlt und das Kind das 18. Lebensjahr noch nicht vollendet hat. Für ein Kind zwischen 12 und 18 Jahren besteht zusätzlich die Voraussetzung, dass das Kind keine SGB II-Leistungen benötigt (auch Hartz IV genannt), das Kind mit der Unterhaltsvorschussleistung von SGB II-Leistungen unabhängig wird oder Sie als Elternteil Einkommen von mindestens 600 Euro Brutto erzielen. Das Einkommen des alleinerziehenden Elternteils, bei dem das Kind lebt, wird nicht angerechnet. Die Unterhaltsvorschusskasse fordert die von ihr gezahlten Leistungen von dem Elternteil zurück, der seiner Unterhaltspflicht trotz bestehender Leistungsfähigkeit nicht nachkommt. Weitere Hinweise über im Einzelfall erforderliche Unterlagen und benötigte Nachweise entnehmen Sie bitte dem Merkblatt zum Unterhaltsvorschussantrag unter Downloads und Infos. Weitere Informationen zum Unterhaltsvorschuss finden Sie in der Broschüre des Bundesministeriums für Familie, Senioren, Frauen und Jugend unter Downloads und Infos. Benötigt werden Antrag auf Unterhaltsvorschussleistungen Hinweis: Bitte stellen Sie für jedes Kind einen Antrag. Geburtsurkunde des Kindes in Kopie Nachweise über die Feststellung der Vaterschaft beziehungsweise den aktuellen Stand der Vaterschaftsfeststellung Vorhandene Unterhaltstitel Für Kinder ab 12 Jahren werden zusätzliche Nachweise benötigt. Diese entnehmen Sie bitte dem Antrag auf Unterhaltsvorschussleistungen. Dies gilt ab dem Monat, in dem der Antrag auf Unterhaltsvorschussleistungen bei der Unterhaltsvorschusskasse eingeht. Anspruchsberechtigte Ausländerinnen und Ausländer Wurde Ihrem Kind beziehungsweise Ihnen als betreuendem Elternteil eine Erlaubnis zur Niederlassung oder zum Aufenthalt erteilt, die zur Ausübung einer Erwerbstätigkeit berechtigt, können Sie Unterhaltsvorschussleistungen beantragen. Weil die schwierige Rechtslage auch Ausnahmen regelt, sollten Sie mit uns sprechen. Ab dem 1. Januar 2022 ergeben sich folgende Unterhaltsvorschussbeträge für Kinder: unter 6 Jahre monatlich 177 Euro von 6 bis 11 Jahre monatlich 236 Euro von 12 bis 17 Jahre monatlich 314 Euro Vorsprache Um Wartezeiten zu vermeiden, vereinbaren Sie bitte zur Vorsprache einen Termin. Am einfachsten ist dies mit einer Nachricht an die Unterhaltsvorschusskasse über unser sicheres Formular. Im Unterschied zu einer E -Mail können hier Ihre persönlichen Daten von Unbefugten nicht mitgelesen werden. Bitte hinterlassen Sie dort: Ihren Namen Ihre Adresse Namen und Geburtsdatum ihres Kindes Ihre Telefonnummer Ihre E -Mail- Adresse Ihr*e Sachbearbeiter*in werden sich dann bei Ihnen melden. Besteht bei Ihnen der Bedarf für eine Rechtsberatung, so nehmen Sie bitte anwaltliche Beratung in Anspruch. Wenn Sie die Mittel für eine Beratung nicht aufbringen können, dann wenden Sie sich bitte an die Rechtsantragsstelle des Amtsgerichts Köln. | B504: Wenn Sie allein ein Kind erziehen , müssen Sie nicht für das Kind bezahlen. Der Eltern-Teil muss bezahlen bei dem das Kind nicht lebt . Wenn der andere Eltern-Teil nicht bezahlt , können Sie Hilfe vom Amt bekommen. Für ein Kind zwischen 12 und 18 Jahren gibt es noch mehr Voraussetzungen : Sie verdienen Brutto wenigstens 600 Euro im Monat . Das Kind braucht kein Hartz 4 . Sie bekommen Unterhalt für das Kind , wenn das Kind kein Hartz 4 bekommt . Oder das Kind braucht kein Hartz 4 mehr , wenn Sie den Unterhalt bekommen. Was wird angerechnet? Das Kinder-Geld wird angerechnet auf den Unterhalts-Vorschuss. Das bedeutet: Wenn Sie Kinder-Geld bekommen, dann verrechnen wir das mit dem Unterhalt. Das Kind bekommt Geld vom Amt. Wenn Ihr Kind Waisen-Rente bekommt, dann verrechnen wir das mit dem Unterhalt. Wenn das Kind nicht mehr zur Schule geht, sondern eigenes Geld hat, dann wird das Einkommen vom Kind angerechnet. Das Einkommen aus dem Vermögen . Was wird nicht angerechnet? Das Vermögen vom Kind wird nicht angerechnet. Das Einkommen von dem Eltern-Teil, bei dem das Kind lebt, wird nicht angerechnet. Aber von dem anderen Eltern-Teil fordern wir den Unterhalt zurück. Dann zahlt die Unterhalts-Vorschuss-Kasse vielleicht den Unterhalt für Ihr Kind. Die Unterhalts-Vorschuss-Kasse holt sich dann das Geld von dem anderen Eltern-Teil, der keinen Unterhalt zahlt . Mehr Infos dazu stehen im Merk-Blatt zum Antrag auf Unterhalt. Mehr Infos zum Unterhalts-Vorschuss finden Sie im Info-Heft vom Bundes-Ministerium für Familie, Senioren, Frauen und Jugend. Antrag Bitte stellen Sie für jedes Kind einen Antrag . Dann müssen Sie den Antrag ausdrucken . Geburts-Urkunde vom Kind Nachweis über die Vaterschaft Weitere Infos zum Unterhalt Für Kinder ab 12 Jahren brauchen wir noch mehr Nachweise. Lesen Sie dazu bitte das Merk-Blatt zum Antrag . Das gilt ab dem Monat, in dem wir Ihren Antrag bekommen . Wenn Sie oder Ihr Kind eine Aufenthalts-Erlaubnis haben. Oder eine Niederlassungs-Erlaubnis . Sprechen Sie bitte mit uns. Der Unterhalts-Vorschuss für Kinder: Unter 6 Jahre: 177 Euro im Monat. Von 6 bis 11 Jahre: 236 Euro im Monat. Von 12 bis 17 Jahre: 314 Euro im Monat. Wichtig: Wenn Sie persönlich kommen wollen, brauchen Sie einen Termin . Schicken Sie am besten eine Nachricht an die Unterhalts-Vorschuss-Kasse . Das können Sie über unser sicheres Formular tun. Dabei bleiben Ihre persönlichen Daten geheim . Niemand kann Ihre Daten lesen. Ihre Daten können von Anderen gelesen werden. Name von Ihrem Kind Geburts-Datum von Ihrem Kind Ihren Namen Ihre Adresse Ihre Telefon-Nummer Ihre E-Mail Ihr Sach-Bearbeiter oder Ihre Sach-Bearbeiterin wird sich dann bei Ihnen melden. Das bedeutet: Wir dürfen Sie nicht in Rechts-Fragen beraten. Wenn Sie eine Rechts-Beratung brauchen, gehen Sie bitte zu einem Anwalt . Wenn Sie nicht genug Geld für einen Anwalt haben, gehen Sie zur Rechts-Antrags-Stelle vom Amts-Gericht Köln . Dann müssen Sie sich nicht an die Öffnungs-Zeiten halten. | C504: 26 | D504: 54 | E504: 408 | F504: 455 | G504: 61.38 | H504: 0.42 | I504: 0.43 | J504: 0.4 | K504: 13 | L504: 2 | M504: 21 | N504: 38 | O504: 1 | P504: 1 | Q504: 1 | R504: 1 | S504: 0 | T504: 0 | U504: 0 | V504: 0 | W504: 1 | X504: 1
A505: In Thüringen sind noch mehr als 1.900 Ausbildungsplätze frei. Das teilte die Bundesagentur für Arbeit mit. Die Arbeitsagentur empfiehlt Unternehmen, auch Bewerber einzustellen, die formal nicht den Anforderungen entsprechen. | B505: In Thüringen sind immer noch viele Ausbildungs-Plätze frei. In dem Bundes-Land Thüringen sind noch viele Ausbildungs-Plätze frei. Markus Behrens ist ein Chef bei der Bundes-Agentur für Arbeit . Außerdem sollen Firmen auch Auszubildende nehmen: | C505: 3 | D505: 4 | E505: 29 | F505: 33 | G505: 21 | H505: 0 | I505: 0.25 | J505: 0.5 | K505: 0 | L505: 0 | M505: 1 | N505: 0 | O505: 0 | P505: 0 | Q505: 1 | R505: 1 | S505: 0 | T505: 0 | U505: 0 | V505: 0 | W505: 1 | X505: 1
A506: Und schafft dabei viel mehr, als nur Überwasserhalten. Sobald die Ferien in Sachsen rum sind, geht es auch für Franziska Meißner wieder los: „Die Kurse richten sich an alle ab zwölf Jahren, die noch nicht oder nicht gut schwimmen können“, erklärt sie. Zwar gebe es auch Fördermöglichkeiten für Kinder aus sozial benachteiligten Familien, die allermeisten Teilnehmer seien aber Flüchtlinge, erzählt Meißner. Der älteste Schwimmnovize sei im letzten Jahr 47 Jahre alt gewesen. Deutsch lernen beim Schwimmen Meißner sagt, zu Beginn habe sie sich durchaus Sorgen gemacht: über Verständigungsprobleme, über Reaktionen auf sie als Frau. Deswegen habe sie zunächst einen männlichen Kollegen um Unterstützung gebeten. Konnten bisher zwei Kurse im Jahr angeboten werden, seien es nun insgesamt sieben auf unterschiedlichen Niveaus. | B506: Und sie hatten meistens wenig Geld. Viele Menschen aus Sachsen und Brandenburg wollten den Flüchtlingen deshalb helfen. Herr Bollmann, Sie sind doch Anwalt? Der deutsche Staat sagt: Die 2 Brüder sollen Deutschland verlassen. Mittlerweile hat Dieter Bollmann viele Abschiebungen verhindert. Manchmal dauert die Arbeits-Suche lange. Nur so können Flüchtlinge ein Leben in Deutschland aufbauen. Außerdem lernen sie bei der Arbeit andere Menschen kennen. Denn Deutsche und Flüchtlinge arbeiten zusammen. Einige Schwimm-Schüler sind 12 Jahre alt. Und einige sind fast 50 Jahr alt. Im Schwimm-Unterricht wird auch Deutsch geübt. Am Anfang hat Franziska Meißner gedacht: Vielleicht wird sie als Frau nicht respektiert. Deshalb hat Franziska Meißner zuerst gemeinsam mit einem männlichen Schwimm-Lehrer unterrichtet. Ihre Kurse sind beliebt. Es werden immer mehr Kurse. | C506: 8 | D506: 18 | E506: 120 | F506: 121 | G506: 39.77 | H506: 0 | I506: 0.11 | J506: 0.71 | K506: 1 | L506: 0 | M506: 7 | N506: 5 | O506: 1 | P506: 1 | Q506: 1 | R506: 1 | S506: 0 | T506: 0 | U506: 0 | V506: 0 | W506: 1 | X506: 1
A507: Der Schultergürtel stellt die Verbindung zwischen Oberarm und Brustbein her und wird gebildet vom Schlüsselbein (Klavikula) und Schulterblatt. Das Schlüsselbein zählt zu den Knochen , die sich Menschen am häufigsten brechen. Ursächlich für einen Schlüsselbeinbruch ist meist ein Unfall. Dabei werden ein direktes und ein indirektes Trauma unterschieden. Beim direkten Trauma kommt es, zum Beispiel durch einen Verkehrsunfall zur einer direkten Krafteinwirkung auf das Schlüsselbein und es bricht. Bei einem indirekten Trauma, zum Beispiel durch einen Sturz auf die Schulter oder den ausgestreckten Arm kommt es zu einer Kraftübertragung auf das Schlüsselbein, wodurch es brechen kann. "Skifahren, Snowboardfahren und Radfahren sind typische Sportarten", meint Unfallchirurg Peter Gutsfeld. Der Arzt kann meist schnell auf einen Schlüsselbeinbruch schließen, sobald er die Schulter untersucht und der Patient seine Beschwerden schildert. Dies kann eine bleibende Fehlstellung (meist eine Verkürzung) verursachen. Eine operative Versorgung ist bei bestimmten Brüchen am schulternahen Ende oder auch bei Brüchen nahe am Brustbein (seltene Bruchform) nötig. Bei der Operation werden die Bruchenden wieder aneinander gefügt (Reposition) und zur Stabilisierung wird eine winkelstabile Platte oder gegebenenfalls ein Nagel verwendet, welcher in den Markraum des Knochens eingebracht wird (intramedulläre Schienung). Einem Schlüsselbeinbruch (Klavikulafraktur) können Sie nur bedingt vorbeugen, da er meist durch einen Sturz, zum Beispiel beim Sport verursacht wird. | B507: Das Schlüsselbein ist ein Knochen zwischen Hals und Schulter. Das Schlüsselbein verbindet den Oberarm mit dem Brustbein. Das Schlüsselbein heißt auch: Klavikula. Knochen können brechen. Auch das Schlüsselbein kann brechen. Die häufigste Ursache für einen Schlüsselbeinbruch ist ein Unfall. Ein Schlüsselbeinbruch muss nämlich behandelt werden. Ärzte unterscheiden zwischen einem direkten Trauma und einem indirekten Trauma: Direktes Trauma: Bei einem direkten Trauma gibt es eine Krafteinwirkung direkt auf das Schlüsselbein. Ein direktes Trauma entsteht zum Beispiel bei einem Verkehrsunfall. Indirektes Trauma: Bei einem indirekten Trauma geht die Krafteinwirkung nicht direkt auf das Schlüsselbein. Die Krafteinwirkung strahlt aber auf das Schlüsselbein aus. Das passiert zum Beispiel bei einem Sturz auf die Schulter. Skifahren Snowboardfahren Radfahren Der Arzt untersucht Sie und kann Ihnen helfen. Manchmal kann der Arzt den Schlüsselbeinbruch mit einer konservativen Therapie behandeln. Der Arzt legt einen speziellen Verband an. So ist der Arm ruhiggestellt und die Schmerzen sind nicht so stark. Dann kann der Bruch gut heilen. Dann hat die betroffene Person eine bleibende Fehlstellung: Der Bruch ist nah am Brustbein. Bei der Operation fügt der Arzt die Knochen wieder zusammen: Mit einer Platte oder mit Nägeln wird der Knochen an seinem Platz befestigt. Dann entfernt der Arzt die Platte oder die Nägel. Sie möchten einen Schlüsselbeinbruch verhindern? Dann können Sie vor allem beim Sport auf Ihre Sicherheit achten: So können Sie schwere Verletzungen bei Stürzen vermeiden. Sie wollen noch mehr über den Schlüsselbeinbruch lesen? | C507: 12 | D507: 31 | E507: 207 | F507: 235 | G507: 67.01 | H507: 0.25 | I507: 0.42 | J507: 0.4 | K507: 10 | L507: 6 | M507: 8 | N507: 8 | O507: 1 | P507: 1 | Q507: 1 | R507: 1 | S507: 0 | T507: 0 | U507: 0 | V507: 0 | W507: 1 | X507: 1
A508: Was genau gilt , ist in den Corona-Schutzverordnungen der Länder festgehalten. Erwachsene Personen, die bereits die Auffrischungsimpfung erhalten haben oder einen Genesenennachweis vorweisen können, sind in Sachsen-Anhalt bei dem 2-G-Plus-Zugangsmodell nicht von der zusätzlichen Testpflicht befreit. Die Frage, ob geboostert und doppelt geimpft plus genesen gleichwertig sind, stellt sich hier also gar nicht. Alle müssen testen. Dazu gehören sowohl Personen mit Boosterimpfung als auch alle, die doppelt geimpft und genesen sind. Meist müssen sie also bei 2G-Plus den zusätzlichen Test trotzdem machen. | B508: Die Test-Pflicht ist bei der 2-G-Plus-Regel in manchen Bundes-Ländern unterschiedlich. Oft sind die Regeln in den Bundes-Ländern sehr verschieden. Zum Beispiel: Bei der Test-Pflicht bei der 2-G-Plus-Regel . Das ist auch in Mittel-Deutschland so. Sachen müssen die Menschen keinen Corona-Test machen. Oder wenn sie 2 Mal ge-impft und geboostert sind. Als ob er geboostert ist. Im Bundes-Land Sachsen-Anhalt müssen alle Menschen einen Corona-Test machen. • und genesen sind. Dann müssen sie keinen Corona-Test machen. | C508: 6 | D508: 11 | E508: 81 | F508: 72 | G508: 14.91 | H508: 0 | I508: 0.09 | J508: 0.33 | K508: 2 | L508: 0 | M508: 1 | N508: 4 | O508: 1 | P508: 1 | Q508: 1 | R508: 1 | S508: 1 | T508: 1 | U508: 1 | V508: 1 | W508: 1 | X508: 1
A509: Bei Opel in Eisenach wird die Produktion des Geländewagens "Grandland X" ab Montag vorerst eingestellt. Die Sorge vieler Mitarbeiter, dass der Standort in Eisenach möglicherweise ganz aufgegeben werden könnte, ist laut Automotive Thüringen aber unbegründet. Dafür wurde das Werk, in dem zuvor die Kleinwagen Corsa und Adam gebaut wurden, zweieinhalb Monate lang umgebaut. | B509: Bei Opel werden für einige Zeit keine Autos gebaut. In der Stadt Eisenach gibt es eine große Auto-Firma . Dort werden viele Autos gebaut. Aber jetzt sollen bis zum nächsten Jahr keine Autos gebaut werden. | C509: 3 | D509: 4 | E509: 53 | F509: 34 | G509: 24.08 | H509: 0.33 | I509: 0.25 | J509: 0.22 | K509: 1 | L509: 0 | M509: 0 | N509: 1 | O509: 1 | P509: 1 | Q509: 1 | R509: 2 | S509: 0 | T509: 0 | U509: 0 | V509: 0 | W509: 1 | X509: 3
A510: Der Alltag ist für den Beamten geregelt. Wer von außen kommt, ist zunächst ein Fremder und muss seinen Start auf die Rolle als Fremder gründen. Für ihn ist die Gesamtsituation neu, und das heißt: unstrukturiert. (…) Das alles wird ihn zu Änderungen disponieren. Die Kommunikationen sind daher nicht sehr gehaltvoll. Er erfährt nur, was er vermutlich schon weiß oder was auf dem Dienstwege zu ihm kommen muss, nicht aber, was von ihm erwartet wird und was er erwarten kann. | B510: Ein Beamter ist ein Arbeiter für den Staat. Das ist aufregend für Beamte. Dann ist er ein Fremder für die Kollegen. Für den Chef sind alle Kollegen und die Firma neu. Für die Firma und die Kollegen ist nur der Chef neu. Das ist alles mein Erfolg. Vielleicht sind manche Kollegen auch besonders nett. Manche Kollegen machen nicht was er sagt. | C510: 6 | D510: 8 | E510: 78 | F510: 61 | G510: 11.14 | H510: 0 | I510: 0.5 | J510: 0 | K510: 1 | L510: 0 | M510: 8 | N510: 4 | O510: 1 | P510: 1 | Q510: 1 | R510: 1 | S510: 1 | T510: 1 | U510: 1 | V510: 1 | W510: 1 | X510: 1
A511: Stromschlag: Sie waren am Dienstag auf einen Güterzug geklettert und hatten einen Stromschlag aus der Oberleitung erlitten. Rettungskräfte bestätigten, dass die Jugendlichen dabei schwere Verletzungen erlitten haben. Die beiden Jungen wurden mit einem Hubschrauber in eine Dresdner Klinik geflogen. | B511: In der Stadt Niesky wurden 2 Jungen durch einen Strom-Schlag schlimm verletzt. Sie sind beim Bahnhof auf einen Container-Zug geklettert. Dort haben sie einen Strom-Schlag von der Oberleitung bekommen. Die 2 Jungen haben schlimme Verbrennungen vom Strom. Die 2 Jungen wurden mit dem Hubschrauber in ein Krankenhaus in der Stadt Dresden geflogen. | C511: 3 | D511: 5 | E511: 39 | F511: 52 | G511: 26.8 | H511: 0 | I511: 0.2 | J511: 0 | K511: 1 | L511: 1 | M511: 1 | N511: 2 | O511: 0 | P511: 0 | Q511: 0 | R511: 0 | S511: 0 | T511: 0 | U511: 0 | V511: 0 | W511: 0 | X511: 0
A512: Die Fertigstellung der Autobahn 143 bei Halle wird deutlich teurer als bisher angenommen. Jetzt ist von 443 Millionen Euro die Rede, das sind 93 Millionen Euro mehr als geplant. Wegen der lockeren Zinspolitik der Europäischen Zentralbank sowie vielen staatlichen Fördermaßnahmen sei zum einen viel Geld auf dem Markt, das jetzt investiert werde. | B512: Die neue Autobahn bei Halle wird teurer. Bei der Stadt Halle wird eine neue Autobahn gebaut. Die neue Autobahn wird doch teurer. Sie wird 443 Millionen Euro kosten. Das ist wegen verschiedenen Sachen so. Das kostet auch viel Geld. • Und die Firma muss viel Geld für Natur-Schutz ausgeben. | C512: 3 | D512: 9 | E512: 52 | F512: 48 | G512: 35.5 | H512: 0 | I512: 0.22 | J512: 0.33 | K512: 1 | L512: 0 | M512: 1 | N512: 3 | O512: 1 | P512: 1 | Q512: 1 | R512: 1 | S512: 0 | T512: 0 | U512: 0 | V512: 0 | W512: 1 | X512: 1
A513: Die Lebenshilfe Main-Taunus ist Mitglied im Landesverband der Lebenshilfe Hessen und in der Bundesvereinigung Lebenshilfe. | B513: Möchten Sie Mitglied bei der Lebenshilfe werden? | C513: 1 | D513: 1 | E513: 15 | F513: 7 | G513: 75.59 | H513: 0 | I513: 0 | J513: 0.2 | K513: 1 | L513: 0 | M513: 0 | N513: 1 | O513: 0 | P513: 0 | Q513: 1 | R513: 1 | S513: 0 | T513: 0 | U513: 0 | V513: 0 | W513: 1 | X513: 1
... A713: Sie ist oft trocken, schuppig, gerötet und juckt in der Haut eines Neurodermitis-Patienten möchte niemand gerne stecken. Sie müssen mit der chronisch entzündlichen, aber nicht ansteckenden Hauterkrankung zurechtkommen, denn eine Heilung gibt es nicht, jedoch viele Therapiemöglichkeiten. Neurodermitis ist eine sehr komplexe Erkrankung, zu deren Entstehung mehrere Faktoren beitragen. Stress kann eine Neurodermitis verschlimmern, jedoch sind umgekehrt die Symptome und hier vor allem der nächtliche Juckreiz seelisch belastend. Typische Symptome sind: allgemein trockene Haut, mit geröteten entzündeten Stellen (Ekzeme), die meist sehr stark jucken flächenhafte Verdickung und Vergröberung der Haut (Lichenifikation) Knötchen und Pusteln Betroffen sind vor allem der Kopf ("Milchschorf") und das Gesicht sowie die Streckseiten der Gliedmaßen (zum Beispiel Außenseite des Arms) und Beugefalten. Bei Kleinkindern und Jugendlichen zeigen sich die Symptome eher an den Gelenkbeugen, im Nacken, an den Handgelenken und Händen. Die Haut wird dicker und gröber, auch Verkrustungen sind typisch. Es beweist jedoch nicht, dass dieses Allergen auch die Neurodermitis beeinflusst. Ohne entsprechende ärztliche Diagnose sollte man nicht auf bestimmte Nahrungsmittel verzichten oder gar langfristig einseitige Diäten einhalten. Patienten mit Neurodermitis sollten ihre Haut täglich mit rückfettenden und feuchtigkeitsspendenden Pflegeprodukten schützen. Wissenschaftliche Belege für die Wirksamkeit dieser Verfahren gibt es nicht, vereinzelt jedoch Hinweise. Selbsthilfegruppen, die Krankenkasse oder der behandelnde Arzt können eventuell mit Kontaktadressen für solche Patienten-Schulungen weiterhelfen. | B713: Sie ist gerötet und juckt stark. Neurodermitis ist nicht ansteckend. Aber Neurodermitis ist eine chronische Erkrankung. Trotzdem kann die Krankheit mit Medikamenten oft gut behandelt werden. Ebenso stark sind dann die Anzeichen der Krankheit. Bei einer Neurodermitis sind bestimmte Hautstellen stark entzündet. Diese Hautstellen jucken dann. Kopf Gesicht Außenseite des Arms Außenseite des Beins in den Beugefalten. Beugefalten sind zum Beispiel hinten am Knie oder in der Armbeuge. Bei Kleinkindern und Jugendlichen ist Neurodermitis vor allem an diesen Stellen häufig: in den Beugefalten der Arme und Beine im Nacken an den Handgelenken an den Händen Bei erwachsenen Personen ist Neurodermitis vor allem an diesen Stellen häufig: in den Beugefalten der Arme und Beine am Nacken an den Händen Dann ist die Haut sehr dick und grob. Es reagiert dann auch auf eigentlich harmlose Reize. Manche Personen vertragen bestimmte Allergene nicht. Zu den möglichen Behandlungen einer Neurodermitis gehören zum Beispiel: besondere Cremes gegen das Jucken und für mehr Feuchtigkeit Therapien mit UV-Strahlen Medikamente Achten Sie außerdem auf diese Dinge: Es gibt Schulungen für betroffene Personen. Informieren Sie sich über die Schulungen bei Ihrer Krankenkasse oder bei Ihrem Arzt. | C713: 12 | D713: 17 | E713: 214 | F713: 187 | G713: 36.03 | H713: 0.25 | I713: 0.24 | J713: 0.43 | K713: 8 | L713: 4 | M713: 5 | N713: 5 | O713: 1 | P713: 1 | Q713: 1 | R713: 1 | S713: 0 | T713: 0 | U713: 0 | V713: 0 | W713: 1 | X713: 1

Sheet Summery
A1: Metric | B1: Normal Mean | C1: Simple Mean | D1: Normal Median | E1: Simple Median | F1: Normal Std Dev | G1: Simple Std Dev | H1: Normal Min | I1: Normal Max | J1: Simple Min | K1: Simple Max | L1: P- Value (Type1) | M1: P- Value (Type2)
A2: Coherence | B2: =AVERAGE(output!H:H) -> 0.21723315 | C2: =AVERAGE(output!I:I) -> 0.32108146 | D2: =MEDIAN(output!H:H) -> 0.2 | E2: =MEDIAN(output!I:I) -> 0.33 | F2: =_xlfn.STDEV.S(output!H:H) -> 0.18709208 | G2: =_xlfn.STDEV.S(output!I:I) -> 0.19103636 | H2: =MIN(output!H:H) -> 0 | I2: =MAX(output!H:H) -> 0.8 | J2: =MIN(output!I:I) -> 0 | K2: =MAX(output!I:I) -> 0.89 | L2: =_xlfn.T.TEST(output!H:H, output!I:I, 2, 1) -> 3.8664209e-27 | M2: =_xlfn.T.TEST(output!I:I, output!J:J, 2, 2) -> 4.7255866e-10
A3: Vocabulary Concreteness | B3: =AVERAGE(output!K:K) -> 4.0926966 | C3: =AVERAGE(output!L:L) -> 2.8876404 | D3: =MEDIAN(output!K:K) -> 2 | E3: =MEDIAN(output!L:L) -> 1 | F3: =_xlfn.STDEV.S(output!K:K) -> 4.8554176 | G3: =_xlfn.STDEV.S(output!L:L) -> 4.1292431 | H3: =MIN(output!K:K) -> 0 | I3: =MAX(output!K:K) -> 34 | J3: =MIN(output!L:L) -> 0 | K3: =MAX(output!L:L) -> 26 | L3: =_xlfn.T.TEST(output!K:K, output!L:L, 2, 1) -> 4.7709733e-22 | M3: =_xlfn.T.TEST(output!L:L, output!M:M, 2, 2) -> 2.6682137e-06
A4: Ambiguity Detection | B4: =AVERAGE(output!M:M) -> 4.0294944 | C4: =AVERAGE(output!N:N) -> 7.2738764 | D4: =MEDIAN(output!M:M) -> 2 | E4: =MEDIAN(output!N:N) -> 3 | F4: =_xlfn.STDEV.S(output!M:M) -> 4.972552 | G4: =_xlfn.STDEV.S(output!N:N) -> 10.216475 | H4: =MIN(output!M:M) -> 0 | I4: =MAX(output!M:M) -> 36 | J4: =MIN(output!N:N) -> 0 | K4: =MAX(output!N:N) -> 69 | L4: =_xlfn.T.TEST(output!M:M, output!N:N, 2, 1) -> 5.2162177e-31 | M4: =_xlfn.T.TEST(output!N:N, output!O:O, 2, 2) -> 1.3128297e-60
A10: Metric | B10: Mean | C10: Median | D10: Std Dev | E10: Min | F10: Max
A11: Semantic Similarity | B11: =AVERAGE(output!G:G) -> 40.412963 | C11: =MEDIAN(output!G:G) -> 40.1 | D11: =_xlfn.STDEV.S(output!G:G) -> 18.071113 | E11: =MIN(output!G:G) -> 0 | F11: =MAX(output!G:G) -> 92.86
A12: Info Preservation Score | B12: =AVERAGE(output!J:J)*100 -> 40.067416 | C12: =MEDIAN(output!J:J)*100 -> 37 | D12: =_xlfn.STDEV.S(output!J:J)*100 -> 27.959554 | E12: =MIN(output!J:J) -> 0 | F12: =MAX(output!J:J) -> 1
A18: Yes / No
A19: Metric | B19: Mean | C19: Median | D19: Std Dev
A20: Explanation Completeness | B20: =AVERAGE(output!O:O) -> 0.66244726 | C20: =MEDIAN(output!O:O) -> 1 | D20: =_xlfn.STDEV.S(output!O:O) -> 0.47320802
A21: Domain Terminology | B21: =AVERAGE(output!Q:Q) -> 0.79465541 | C21: =MEDIAN(output!Q:Q) -> 1 | D21: =_xlfn.STDEV.S(output!Q:Q) -> 0.40423757
A22: Metaphor Appropriateness | B22: =AVERAGE(output!S:S) -> 0.0604782 | C22: =MEDIAN(output!S:S) -> 0 | D22: =_xlfn.STDEV.S(output!S:S) -> 0.2385385
A23: Example Relevance | B23: =AVERAGE(output!U:U) -> 0.12658228 | C23: =MEDIAN(output!U:U) -> 0 | D23: =_xlfn.STDEV.S(output!U:U) -> 0.33273852
A24: Info Preservation | B24: =AVERAGE(output!W:W) -> 0.90998594 | C24: =MEDIAN(output!W:W) -> 1 | D24: =_xlfn.STDEV.S(output!W:W) -> 0.28640339
A28: Count
A29: Metric | B29: Mean | C29: Median | D29: Std Dev | E29: Min | F29: Max
A30: Explanation Completeness | B30: =AVERAGE(output!P:P) -> 0.67229255 | C30: =MEDIAN(output!P:P) -> 1 | D30: =_xlfn.STDEV.S(output!P:P) -> 0.49311337 | E30: =MIN(output!P:P) -> 0 | F30: =MAX(output!P:P) -> 3
A31: Domain Terminology | B31: =AVERAGE(output!R:R) -> 0.87482419 | C31: =MEDIAN(output!R:R) -> 1 | D31: =_xlfn.STDEV.S(output!R:R) -> 0.61878954 | E31: =MIN(output!R:R) -> 0 | F31: =MAX(output!R:R) -> 5
A32: Metaphor Appropriateness | B32: =AVERAGE(output!T:T) -> 0.0604782 | C32: =MEDIAN(output!T:T) -> 0 | D32: =_xlfn.STDEV.S(output!T:T) -> 0.2385385 | E32: =MIN(output!T:T) -> 0 | F32: =MAX(output!T:T) -> 1
A33: Example Relevance | B33: =AVERAGE(output!V:V) -> 0.12798875 | C33: =MEDIAN(output!V:V) -> 0 | D33: =_xlfn.STDEV.S(output!V:V) -> 0.33849922 | E33: =MIN(output!V:V) -> 0 | F33: =MAX(output!V:V) -> 2
A34: Info Preservation | B34: =AVERAGE(output!X:X) -> 1.1308017 | C34: =MEDIAN(output!X:X) -> 1 | D34: =_xlfn.STDEV.S(output!X:X) -> 0.70893239 | E34: =MIN(output!X:X) -> 0 | F34: =MAX(output!X:X) -> 5
